[
  {
    "id": 1,
    "title": "太阳系行星",
    "content": "太阳系中有八大行星，按距离太阳由近到远依次为：水星、金星、地球、火星、木星、土星、天王星、海王星。",
    "image": "",
    "category": "天文"
  },
  {
    "id": 2,
    "title": "水的三态变化",
    "content": "水有三种状态：固态（冰）、液态（水）、气态（水蒸气）。三态变化是物理变化，由温度变化引起。",
    "image": "",
    "category": "物理"
  },
  {
    "id": 3,
    "title": "哺乳动物特征",
    "content": "哺乳动物的主要特征：胎生、哺乳、体表被毛、体温恒定、心脏四腔。",
    "image": "",
    "category": "生物"
  },
  {
    "id": 4,
    "title": "光合作用",
    "content": "光合作用是植物利用光能将二氧化碳和水转化为有机物并释放氧气的过程，主要场所是叶绿体。",
    "image": "",
    "category": "生物"
  },
  {
    "id": 5,
    "title": "简单机械",
    "content": "简单机械包括：杠杆、滑轮、轮轴、斜面、楔、螺旋。",
    "image": "",
    "category": "物理"
  },
  {
    "id": 6,
    "title": "声音传播介质",
    "content": "声音需要介质传播，介质密度越大，传播速度越快。声音不能在真空中传播。",
    "image": "",
    "category": "物理"
  },
  {
    "id": 7,
    "title": "导体与绝缘体",
    "content": "导体是容易导电的物质，如金属、人体、大地等；绝缘体是不容易导电的物质，如塑料、橡胶、玻璃等。",
    "image": "",
    "category": "物理"
  },
  {
    "id": 8,
    "title": "地球自转",
    "content": "地球自西向东自转，周期约为24小时，产生昼夜交替现象。",
    "image": "",
    "category": "地理"
  },
  {
    "id": 9,
    "title": "可再生能源",
    "content": "可再生能源是可以不断再生的能源，如太阳能、风能、水能、生物质能等。",
    "image": "",
    "category": "能源"
  },
  {
    "id": 10,
    "title": "呼吸系统",
    "content": "人体呼吸系统包括呼吸道和肺，肺是气体交换的主要场所。",
    "image": "",
    "category": "生物"
  },
  {
    "title": "晶体",
    "content": "晶体是一种内部结构非常规则、粒子排列呈周期性重复的固态物质",
    "category": "物理",
    "image": "",
    "id": 11
  }
]